Workbook

Sheet Data
B1: On The Blvd Proforma - B
C3: Building Data
C4: Square Feet | D4: 62749
C5: Rent Per Square Foot | D5: 17.65
C6: Other Income | D6: 10200
C7: Vacancy | D7: 0.1
G8: Financing Data
C9: First Year Operating Statement
B10: Potential Rental Income | D10: =D4*D5 -> 1107519.8 | G10: Loan Interest Rate | H10: 0.05
B11: Vacancy & Credit Loss | D11: =D7 -> 0.1 | G11: Loan Amortization (years) | H11: 15
B12: Effective Rental Income | D12: =D10*(1-D11) -> 996767.86 | G12: LTV | H12: 0.22
B13: Other Income | D13: 10200 | G13: DSCR | H13: 1.25
B14: Gross Operating Income | D14: =D12+D13 -> 1006967.9 | G14: Loan Amount (LTV) | H14: 1500000
B15: Property Taxes | D15: 54175.81
B16: Insurance | D16: 61780.56 | G16: Loan Amount | H16: =MIN(H14,H15) -> 1500000
B17: Maintenance | D17: 66892 | F17: Appraised Vlue | H17: 6700000
B18: Management Fee | D18: 195000 | G18: Monthly Debt Service | H18: 11918.73
B19: Reserves for Replacement | D19: 24000 | G19: Annual Debt Service | H19: =H18*12 -> 143024.76
B20: Auto Expenses | D20: 8400
B21: Total Expenses | D21: =SUM(D15:D20) -> 410248.37
B22: Net Operating Income | D22: =D14-D21 -> 596719.49
B23: Debt Service | D23: =H19 -> 143024.76
B24: Cash Flow Before Tax | D24: =D22-D23 -> 453694.73

Sheet Proforma
B1: Proforma
C3: Year 1 | D3: Year 2 | E3: Year 3 | F3: Year 4 | G3: Year 5 | H3: Year 6
B4: Gross Potential Income | C4: =Data!D10 -> 1107519.8 | D4: =C4*(1+Data!#REF!) -> #REF! | E4: =D4*(1+Data!#REF!) -> #REF! | F4: =E4*(1+Data!#REF!) -> #REF! | G4: =F4*(1+Data!#REF!) -> #REF! | H4: =G4*(1+Data!#REF!) -> #REF!
B5: Vacancy & Credit Loss | C5: =Data!D11*C4 -> 110751.98 | D5: =Data!#REF! -> #REF! | E5: =Data!#REF! -> #REF! | F5: =Data!#REF! -> #REF! | G5: =Data!#REF! -> #REF! | H5: =Data!#REF! -> #REF!
B6: Effective Rental Income | C6: =C4-C5 -> 996767.86 | D6: =D4*(1-D5) -> #REF! | E6: =E4*(1-E5) -> #REF! | F6: =F4*(1-F5) -> #REF! | G6: =G4*(1-G5) -> #REF! | H6: =H4*(1-H5) -> #REF!
B7: Other Income | C7: =Data!D13 -> 10200 | D7: =C7*(1+Data!#REF!) -> #REF! | E7: =D7*(1+Data!#REF!) -> #REF! | F7: =E7*(1+Data!#REF!) -> #REF! | G7: =F7*(1+Data!#REF!) -> #REF! | H7: =G7*(1+Data!#REF!) -> #REF!
B8: Gross Operating Income | C8: =C6+C7 -> 1006967.9 | D8: =D6+D7 -> #REF! | E8: =E6+E7 -> #REF! | F8: =F6+F7 -> #REF! | G8: =G6+G7 -> #REF! | H8: =H6+H7 -> #REF!
B9: Operating Expenses | C9: =Data!D21 -> 410248.37 | D9: =C9*(1+Data!#REF!) -> #REF! | E9: =D9*(1+Data!#REF!) -> #REF! | F9: =E9*(1+Data!#REF!) -> #REF! | G9: =F9*(1+Data!#REF!) -> #REF! | H9: =G9*(1+Data!#REF!) -> #REF!
B10: Net Operating Income | C10: =C8-C9 -> 596719.49 | D10: =D8-D9 -> #REF! | E10: =E8-E9 -> #REF! | F10: =F8-F9 -> #REF! | G10: =G8-G9 -> #REF! | H10: =H8-H9 -> #REF!
B11: Debt Service | C11: =Data!H19 -> 143024.76 | D11: =Data!H19 -> 143024.76 | E11: =Data!H19 -> 143024.76 | F11: =Data!H19 -> 143024.76 | G11: =Data!H19 -> 143024.76
B12: Cash Flow Before Tax | C12: =C10-C11 -> 453694.73 | D12: =D10-D11 -> #REF! | E12: =E10-E11 -> #REF! | F12: =F10-F11 -> #REF! | G12: =G10-G11 -> #REF!
B16: Future Sale Value | G16: =H10/Data!$H$5 -> #REF!
B17: less: Cost of Sale | G17: =G16*Data!H6 -> #REF!
B18: less: Loan Balance | G18: =PV(Data!$H$10/12,Proforma!G22,-Data!H18) -> 1123714
B19: Net Sale Proceeds | G19: =G16-G17-G18 -> #REF!
B22: Remaining Payments | C22: =Data!$H$11*12-12 -> 168 | D22: =C22-12 -> 156 | E22: =D22-12 -> 144 | F22: =E22-12 -> 132 | G22: =F22-12 -> 120
